graphscope_jupyter/__init__.py
graphscope_jupyter/_frontend.py
graphscope_jupyter/_version.py
graphscope_jupyter/graphin.py
graphscope_jupyter/nbextension/__init__.py
graphscope_jupyter/nbextension/static/index.js
graphscope_jupyter/nbextension/static/index.js.map
graphscope_jupyter-0.4.1.data/data/etc/jupyter/nbconfig/notebook.d/graphscope-jupyter.json
graphscope_jupyter-0.4.1.data/data/share/jupyter/nbextensions/graphscope-jupyter/index.js
graphscope_jupyter-0.4.1.data/data/share/jupyter/nbextensions/graphscope-jupyter/index.js.map
graphscope_jupyter-0.4.1.dist-info/LICENSE
graphscope_jupyter-0.4.1.dist-info/METADATA
graphscope_jupyter-0.4.1.dist-info/WHEEL
graphscope_jupyter-0.4.1.dist-info/top_level.txt
graphscope_jupyter-0.4.1.dist-info/RECORD
