Metadata-Version: 2.1
Name: graphscope-jupyter
Version: 0.4.1
Summary: Python implementation of the graph visualization tool Graphin.
Home-page: https://github.com/alibaba/GraphScope
Author: Alibaba Damo Academy
Author-email: graphscope@alibaba-inc.com
License: BSD
Keywords: Jupyter,Widgets,IPython
Platform: Linux
Platform: Mac OS X
Platform: Windows
Classifier: Intended Audience :: Developers
Classifier: Intended Audience :: Science/Research
Classifier: License :: OSI Approved :: BSD License
Classifier: Programming Language :: Python
Classifier: Programming Language :: Python :: 3
Classifier: Programming Language :: Python :: 3.4
Classifier: Programming Language :: Python :: 3.5
Classifier: Programming Language :: Python :: 3.6
Classifier: Programming Language :: Python :: 3.7
Classifier: Framework :: Jupyter
Requires-Dist: ipywidgets (>=7.0.0)
Requires-Dist: spectate (>=0.4.1)
Requires-Dist: traitlets
Requires-Dist: networkx
Provides-Extra: docs
Requires-Dist: sphinx ; extra == 'docs'
Requires-Dist: sphinx-rtd-theme ; extra == 'docs'
Requires-Dist: sphinx-autobuild (>=2020.9.1) ; extra == 'docs'
Requires-Dist: jupyter-sphinx (>=0.3.1) ; extra == 'docs'
Requires-Dist: sphinx-copybutton ; extra == 'docs'
Requires-Dist: nbsphinx ; extra == 'docs'
Requires-Dist: nbsphinx-link ; extra == 'docs'
Requires-Dist: networkx ; extra == 'docs'
Requires-Dist: pandas ; extra == 'docs'
Provides-Extra: examples
Requires-Dist: pandas ; extra == 'examples'
Provides-Extra: test
Requires-Dist: pytest (>4.6) ; extra == 'test'
Requires-Dist: pytest-cov ; extra == 'test'
Requires-Dist: nbval ; extra == 'test'
Requires-Dist: pandas ; extra == 'test'
